lxmfy/__init__.py
lxmfy/__version__.py
lxmfy/attachments.py
lxmfy/cli.py
lxmfy/cogs_core.py
lxmfy/commands.py
lxmfy/config.py
lxmfy/core.py
lxmfy/events.py
lxmfy/help.py
lxmfy/middleware.py
lxmfy/moderation.py
lxmfy/permissions.py
lxmfy/scheduler.py
lxmfy/signatures.py
lxmfy/storage.py
lxmfy/templates/__init__.py
lxmfy/templates/cog_test_bot.py
lxmfy/templates/echo_bot.py
lxmfy/templates/note_bot.py
lxmfy/templates/reminder_bot.py
lxmfy/transport.py
lxmfy/validation.py
lxmfy-1.0.3.dist-info/METADATA
lxmfy-1.0.3.dist-info/WHEEL
lxmfy-1.0.3.dist-info/entry_points.txt
lxmfy-1.0.3.dist-info/licenses/LICENSE
lxmfy-1.0.3.dist-info/RECORD
