Metadata-Version: 2.4
Name: lxmfy
Version: 1.0.3
Summary: LXMF bot framework for creating bots for the Reticulum Network
License-File: LICENSE
Author: Quad4
Requires-Python: >=3.11
Classifier: Programming Language :: Python :: 3
Classifier: Programming Language :: Python :: 3.11
Classifier: Programming Language :: Python :: 3.12
Classifier: Programming Language :: Python :: 3.13
Classifier: Programming Language :: Python :: 3.14
Requires-Dist: lxmf (>=0.9.0)
Requires-Dist: rns (>=1.0.1)
